ChordalPy/Chord.py
ChordalPy/StringChordParser.py
ChordalPy/Tables.py
ChordalPy/Transposers.py
ChordalPy/__init__.py
PyChord/Chord.py
PyChord/StringChordParser.py
PyChord/Tables.py
PyChord/Transposers.py
PyChord/__init__.py
ChordalPy-0.1.0.dist-info/LICENSE
ChordalPy-0.1.0.dist-info/METADATA
ChordalPy-0.1.0.dist-info/WHEEL
ChordalPy-0.1.0.dist-info/top_level.txt
ChordalPy-0.1.0.dist-info/RECORD
