Metadata-Version: 2.1
Name: ChordalPy
Version: 0.1.0
Summary: Parse and manipulate musical chords
Home-page: https://github.com/P-bibs/ChordalPy
Author: P-bibs
Author-email: author@example.com
License: UNKNOWN
Platform: UNKNOWN
Classifier: Programming Language :: Python :: 3
Classifier: License :: OSI Approved :: MIT License
Classifier: Operating System :: OS Independent
